Metadata-Version: 1.0
Name: directory-to-sql
Version: 0.1.1
Summary: Get a SQL database of file directory data.
Home-page: http://github.com/hydrospanner/directory_to_sql
Author: John Tucker
Author-email: UNKNOWN
License: MIT
Platform: UNKNOWN
